[
  {
    "id": 1,
    "decisionId": "DEC-2025-001",
    "decisionType": "Budget Allocation",
    "subject": "Strategic project funding - Ikeja Mtendere",
    "description": "Approve budget allocation for infrastructure in Ikeja",
    "amount": 2970578.0,
    "requestedBy": "Director of Finance",
    "requestDate": "2025-12-23T00:00:00",
    "status": "Rejected",
    "approvedBy": "Town Clerk - Ikeja LGA",
    "approvalDate": "2026-01-03T00:00:00",
    "priority": "High",
    "impact": "Improved infrastructure in high-density areas",
    "aiRecommendation": "Review budget",
    "confidenceScore": 74.1,
    "notes": "Standard procedure - Ikeja LGA",
    "createdDate": "2025-12-08T00:00:00"
  },
  {
    "id": 2,
    "decisionId": "DEC-2025-002",
    "decisionType": "Policy",
    "subject": "Emergency facility upgrade - Ikeja City Centre",
    "description": "Approve budget allocation for infrastructure in Ikeja",
    "amount": 908530.0,
    "requestedBy": "Director of Administration",
    "requestDate": "2025-12-25T00:00:00",
    "status": "Under Review",
    "approvedBy": "Council Committee",
    "approvalDate": "2025-12-21T00:00:00",
    "priority": "Medium",
    "impact": "Improved community welfare in commercial areas",
    "aiRecommendation": "Defer pending review",
    "confidenceScore": 71.1,
    "notes": "Urgent action required - Ikeja LGA",
    "createdDate": "2025-12-21T00:00:00"
  },
  {
    "id": 3,
    "decisionId": "DEC-2025-003",
    "decisionType": "Policy",
    "subject": "Strategic equipment purchase - Ikeja Mtendere",
    "description": "Approve budget allocation for services in Ikeja",
    "amount": 7944205.0,
    "requestedBy": "Director of Health",
    "requestDate": "2026-01-08T00:00:00",
    "status": "Approved",
    "approvedBy": "Finance Director",
    "approvalDate": null,
    "priority": "Low",
    "impact": "Improved community welfare in residential areas",
    "aiRecommendation": "Defer pending review",
    "confidenceScore": 78.9,
    "notes": "Urgent action required - Ikeja LGA",
    "createdDate": "2025-12-08T00:00:00"
  },
  {
    "id": 4,
    "decisionId": "DEC-2025-004",
    "decisionType": "Procurement",
    "subject": "Planned equipment purchase - Ikeja Kanyama",
    "description": "Approve procurement for facilities in Ikeja",
    "amount": 16016912.0,
    "requestedBy": "Director of Environment",
    "requestDate": "2025-12-26T00:00:00",
    "status": "Approved",
    "approvedBy": null,
    "approvalDate": null,
    "priority": "Low",
    "impact": "Improved efficiency in low-density areas",
    "aiRecommendation": "Review budget",
    "confidenceScore": 86.4,
    "notes": "Urgent action required - Ikeja LGA",
    "createdDate": "2025-12-27T00:00:00"
  },
  {
    "id": 5,
    "decisionId": "DEC-2025-005",
    "decisionType": "Budget Allocation",
    "subject": "Strategic road repairs - Ikeja Kanyama",
    "description": "Approve procurement for services in Ikeja",
    "amount": 10843543.0,
    "requestedBy": "Director of Administration",
    "requestDate": "2025-11-23T00:00:00",
    "status": "Approved",
    "approvedBy": null,
    "approvalDate": "2026-01-04T00:00:00",
    "priority": "Low",
    "impact": "Improved efficiency in residential areas",
    "aiRecommendation": "Defer pending review",
    "confidenceScore": 89.5,
    "notes": "Urgent action required - Ikeja LGA",
    "createdDate": "2025-12-10T00:00:00"
  },
  {
    "id": 6,
    "decisionId": "DEC-2025-006",
    "decisionType": "Budget Allocation",
    "subject": "Strategic road repairs - Ikeja Chilenje",
    "description": "Approve procurement for equipment in Ikeja",
    "amount": 6247262.0,
    "requestedBy": "Director of Environment",
    "requestDate": "2025-11-29T00:00:00",
    "status": "Pending",
    "approvedBy": null,
    "approvalDate": null,
    "priority": "Low",
    "impact": "Improved community welfare in low-density areas",
    "aiRecommendation": "Approve - Critical need",
    "confidenceScore": 95.9,
    "notes": "Standard procedure - Ikeja LGA",
    "createdDate": "2025-11-28T00:00:00"
  },
  {
    "id": 7,
    "decisionId": "DEC-2025-007",
    "decisionType": "Procurement",
    "subject": "Strategic facility upgrade - Ikeja Chilenje",
    "description": "Approve procurement for facilities in Ikeja",
    "amount": 13544568.0,
    "requestedBy": "Director of Administration",
    "requestDate": "2025-11-19T00:00:00",
    "status": "Rejected",
    "approvedBy": null,
    "approvalDate": null,
    "priority": "Critical",
    "impact": "Improved infrastructure in commercial areas",
    "aiRecommendation": "Review budget",
    "confidenceScore": 80.0,
    "notes": "Standard procedure - Ikeja LGA",
    "createdDate": "2025-12-08T00:00:00"
  },
  {
    "id": 8,
    "decisionId": "DEC-2025-008",
    "decisionType": "Budget Allocation",
    "subject": "Planned facility upgrade - Ikeja City Centre",
    "description": "Approve investment for equipment in Ikeja",
    "amount": 6967815.0,
    "requestedBy": "Director of Health",
    "requestDate": "2025-12-21T00:00:00",
    "status": "Pending",
    "approvedBy": null,
    "approvalDate": null,
    "priority": "High",
    "impact": "Improved community welfare in residential areas",
    "aiRecommendation": "Approve with conditions",
    "confidenceScore": 93.4,
    "notes": "Standard procedure - Ikeja LGA",
    "createdDate": "2025-12-10T00:00:00"
  },
  {
    "id": 9,
    "decisionId": "DEC-2025-009",
    "decisionType": "Procurement",
    "subject": "Strategic facility upgrade - Ikeja Chilenje",
    "description": "Approve procurement for facilities in Ikeja",
    "amount": 19836993.0,
    "requestedBy": "Director of Planning",
    "requestDate": "2026-01-06T00:00:00",
    "status": "Under Review",
    "approvedBy": null,
    "approvalDate": "2025-12-24T00:00:00",
    "priority": "High",
    "impact": "Improved services in high-density areas",
    "aiRecommendation": "Defer pending review",
    "confidenceScore": 75.9,
    "notes": "Urgent action required - Ikeja LGA",
    "createdDate": "2025-11-28T00:00:00"
  },
  {
    "id": 10,
    "decisionId": "DEC-2025-010",
    "decisionType": "Procurement",
    "subject": "Planned equipment purchase - Ikeja Kanyama",
    "description": "Approve budget allocation for facilities in Ikeja",
    "amount": 18997954.0,
    "requestedBy": "Director of Environment",
    "requestDate": "2025-12-24T00:00:00",
    "status": "Pending",
    "approvedBy": null,
    "approvalDate": "2025-12-21T00:00:00",
    "priority": "High",
    "impact": "Improved efficiency in high-density areas",
    "aiRecommendation": "Review budget",
    "confidenceScore": 79.3,
    "notes": "Standard procedure - Ikeja LGA",
    "createdDate": "2025-12-25T00:00:00"
  },
  {
    "id": 11,
    "decisionId": "DEC-2025-011",
    "decisionType": "Budget Allocation",
    "subject": "Planned equipment purchase - Ikeja City Centre",
    "description": "Approve budget allocation for services in Ikeja",
    "amount": 12246773.0,
    "requestedBy": "Director of Finance",
    "requestDate": "2025-12-10T00:00:00",
    "status": "Under Review",
    "approvedBy": null,
    "approvalDate": null,
    "priority": "Critical",
    "impact": "Improved community welfare in residential areas",
    "aiRecommendation": "Defer pending review",
    "confidenceScore": 86.5,
    "notes": "Standard procedure - Ikeja LGA",
    "createdDate": "2025-12-03T00:00:00"
  },
  {
    "id": 12,
    "decisionId": "DEC-2025-012",
    "decisionType": "Infrastructure",
    "subject": "Strategic project funding - Ikeja Mtendere",
    "description": "Approve procurement for infrastructure in Ikeja",
    "amount": 16977704.0,
    "requestedBy": "Director of Environment",
    "requestDate": "2026-01-07T00:00:00",
    "status": "Rejected",
    "approvedBy": "Finance Director",
    "approvalDate": "2025-12-31T00:00:00",
    "priority": "Low",
    "impact": "Improved efficiency in low-density areas",
    "aiRecommendation": "Review budget",
    "confidenceScore": 94.5,
    "notes": "Standard procedure - Ikeja LGA",
    "createdDate": "2025-12-10T00:00:00"
  },
  {
    "id": 13,
    "decisionId": "DEC-2025-013",
    "decisionType": "Investment",
    "subject": "Strategic road repairs - Ikeja Chilenje",
    "description": "Approve procurement for facilities in Ikeja",
    "amount": 19925288.0,
    "requestedBy": "Director of Finance",
    "requestDate": "2025-12-23T00:00:00",
    "status": "Under Review",
    "approvedBy": null,
    "approvalDate": "2026-01-03T00:00:00",
    "priority": "Low",
    "impact": "Improved community welfare in high-density areas",
    "aiRecommendation": "Review budget",
    "confidenceScore": 80.3,
    "notes": "Standard procedure - Ikeja LGA",
    "createdDate": "2025-12-07T00:00:00"
  },
  {
    "id": 14,
    "decisionId": "DEC-2025-014",
    "decisionType": "Budget Allocation",
    "subject": "Strategic road repairs - Ikeja Mtendere",
    "description": "Approve procurement for facilities in Ikeja",
    "amount": 12378597.0,
    "requestedBy": "Director of Environment",
    "requestDate": "2025-11-29T00:00:00",
    "status": "Approved",
    "approvedBy": null,
    "approvalDate": null,
    "priority": "High",
    "impact": "Improved infrastructure in high-density areas",
    "aiRecommendation": "Approve - Critical need",
    "confidenceScore": 89.7,
    "notes": "Standard procedure - Ikeja LGA",
    "createdDate": "2025-12-22T00:00:00"
  },
  {
    "id": 15,
    "decisionId": "DEC-2025-015",
    "decisionType": "Budget Allocation",
    "subject": "Planned project funding - Ikeja Kanyama",
    "description": "Approve budget allocation for facilities in Ikeja",
    "amount": 16111304.0,
    "requestedBy": "Director of Finance",
    "requestDate": "2026-01-08T00:00:00",
    "status": "Rejected",
    "approvedBy": "Finance Director",
    "approvalDate": null,
    "priority": "Low",
    "impact": "Improved infrastructure in high-density areas",
    "aiRecommendation": "Review budget",
    "confidenceScore": 73.0,
    "notes": "Standard procedure - Ikeja LGA",
    "createdDate": "2025-12-13T00:00:00"
  },
  {
    "id": 16,
    "decisionId": "DEC-2025-016",
    "decisionType": "Budget Allocation",
    "subject": "Emergency service expansion - Ikeja City Centre",
    "description": "Approve procurement for infrastructure in Ikeja",
    "amount": 4717091.0,
    "requestedBy": "Director of Administration",
    "requestDate": "2025-12-01T00:00:00",
    "status": "Approved",
    "approvedBy": "Town Clerk - Ikeja LGA",
    "approvalDate": "2026-01-11T00:00:00",
    "priority": "Critical",
    "impact": "Improved infrastructure in residential areas",
    "aiRecommendation": "Review budget",
    "confidenceScore": 94.4,
    "notes": "Standard procedure - Ikeja LGA",
    "createdDate": "2025-12-05T00:00:00"
  },
  {
    "id": 17,
    "decisionId": "DEC-2025-017",
    "decisionType": "Budget Allocation",
    "subject": "Emergency project funding - Ikeja Rhodes Park",
    "description": "Approve investment for infrastructure in Ikeja",
    "amount": 18095241.0,
    "requestedBy": "Director of Planning",
    "requestDate": "2026-01-04T00:00:00",
    "status": "Rejected",
    "approvedBy": null,
    "approvalDate": null,
    "priority": "Critical",
    "impact": "Improved infrastructure in commercial areas",
    "aiRecommendation": "Review budget",
    "confidenceScore": 73.8,
    "notes": "Standard procedure - Ikeja LGA",
    "createdDate": "2025-11-22T00:00:00"
  },
  {
    "id": 18,
    "decisionId": "DEC-2025-018",
    "decisionType": "Contract",
    "subject": "Strategic facility upgrade - Ikeja Kanyama",
    "description": "Approve procurement for services in Ikeja",
    "amount": 14118804.0,
    "requestedBy": "Director of Health",
    "requestDate": "2025-11-26T00:00:00",
    "status": "Approved",
    "approvedBy": null,
    "approvalDate": "2026-01-01T00:00:00",
    "priority": "Medium",
    "impact": "Improved infrastructure in low-density areas",
    "aiRecommendation": "Approve - Critical need",
    "confidenceScore": 96.3,
    "notes": "Standard procedure - Ikeja LGA",
    "createdDate": "2025-11-21T00:00:00"
  },
  {
    "id": 19,
    "decisionId": "DEC-2025-019",
    "decisionType": "Policy",
    "subject": "Strategic facility upgrade - Ikeja Rhodes Park",
    "description": "Approve investment for infrastructure in Ikeja",
    "amount": 17523289.0,
    "requestedBy": "Director of Planning",
    "requestDate": "2025-12-23T00:00:00",
    "status": "Rejected",
    "approvedBy": null,
    "approvalDate": "2026-01-07T00:00:00",
    "priority": "High",
    "impact": "Improved infrastructure in residential areas",
    "aiRecommendation": "Approve with conditions",
    "confidenceScore": 89.4,
    "notes": "Standard procedure - Ikeja LGA",
    "createdDate": "2025-11-29T00:00:00"
  },
  {
    "id": 20,
    "decisionId": "DEC-2025-020",
    "decisionType": "Budget Allocation",
    "subject": "Strategic facility upgrade - Ikeja City Centre",
    "description": "Approve investment for facilities in Ikeja",
    "amount": 18460337.0,
    "requestedBy": "Director of Environment",
    "requestDate": "2026-01-08T00:00:00",
    "status": "Under Review",
    "approvedBy": null,
    "approvalDate": null,
    "priority": "Medium",
    "impact": "Improved efficiency in low-density areas",
    "aiRecommendation": "Review budget",
    "confidenceScore": 89.9,
    "notes": "Standard procedure - Ikeja LGA",
    "createdDate": "2025-11-30T00:00:00"
  },
  {
    "id": 21,
    "decisionId": "DEC-2025-021",
    "decisionType": "Investment",
    "subject": "Emergency project funding - Ikeja Mtendere",
    "description": "Approve budget allocation for infrastructure in Ikeja",
    "amount": 15086906.0,
    "requestedBy": "Director of Planning",
    "requestDate": "2025-11-22T00:00:00",
    "status": "Pending",
    "approvedBy": "Finance Director",
    "approvalDate": "2026-01-11T00:00:00",
    "priority": "High",
    "impact": "Improved efficiency in residential areas",
    "aiRecommendation": "Approve with conditions",
    "confidenceScore": 77.8,
    "notes": "Standard procedure - Ikeja LGA",
    "createdDate": "2025-12-18T00:00:00"
  },
  {
    "id": 22,
    "decisionId": "DEC-2025-022",
    "decisionType": "Procurement",
    "subject": "Planned facility upgrade - Ikeja City Centre",
    "description": "Approve procurement for facilities in Ikeja",
    "amount": 4104608.0,
    "requestedBy": "Director of Administration",
    "requestDate": "2025-12-05T00:00:00",
    "status": "Pending",
    "approvedBy": null,
    "approvalDate": "2026-01-17T00:00:00",
    "priority": "Medium",
    "impact": "Improved efficiency in residential areas",
    "aiRecommendation": "Defer pending review",
    "confidenceScore": 83.8,
    "notes": "Urgent action required - Ikeja LGA",
    "createdDate": "2025-11-14T00:00:00"
  },
  {
    "id": 23,
    "decisionId": "DEC-2025-023",
    "decisionType": "Contract",
    "subject": "Strategic road repairs - Ikeja Kanyama",
    "description": "Approve budget allocation for infrastructure in Ikeja",
    "amount": 15341323.0,
    "requestedBy": "Director of Public Works",
    "requestDate": "2025-12-25T00:00:00",
    "status": "Under Review",
    "approvedBy": null,
    "approvalDate": null,
    "priority": "Medium",
    "impact": "Improved services in high-density areas",
    "aiRecommendation": "Defer pending review",
    "confidenceScore": 93.9,
    "notes": "Standard procedure - Ikeja LGA",
    "createdDate": "2025-12-23T00:00:00"
  },
  {
    "id": 24,
    "decisionId": "DEC-2025-024",
    "decisionType": "Contract",
    "subject": "Strategic facility upgrade - Ikeja Chilenje",
    "description": "Approve investment for equipment in Ikeja",
    "amount": 17174533.0,
    "requestedBy": "Director of Finance",
    "requestDate": "2025-12-22T00:00:00",
    "status": "Approved",
    "approvedBy": null,
    "approvalDate": "2026-01-01T00:00:00",
    "priority": "High",
    "impact": "Improved services in residential areas",
    "aiRecommendation": "Approve - Critical need",
    "confidenceScore": 89.3,
    "notes": "Standard procedure - Ikeja LGA",
    "createdDate": "2026-01-01T00:00:00"
  },
  {
    "id": 25,
    "decisionId": "DEC-2025-025",
    "decisionType": "Budget Allocation",
    "subject": "Planned service expansion - Ikeja City Centre",
    "description": "Approve budget allocation for infrastructure in Ikeja",
    "amount": 10408765.0,
    "requestedBy": "Director of Public Works",
    "requestDate": "2025-12-28T00:00:00",
    "status": "Rejected",
    "approvedBy": null,
    "approvalDate": null,
    "priority": "Low",
    "impact": "Improved infrastructure in commercial areas",
    "aiRecommendation": "Review budget",
    "confidenceScore": 80.2,
    "notes": "Urgent action required - Ikeja LGA",
    "createdDate": "2025-12-18T00:00:00"
  },
  {
    "id": 26,
    "decisionId": "DEC-2025-026",
    "decisionType": "Infrastructure",
    "subject": "Strategic service expansion - Ikeja City Centre",
    "description": "Approve procurement for services in Ikeja",
    "amount": 19486350.0,
    "requestedBy": "Director of Health",
    "requestDate": "2026-01-04T00:00:00",
    "status": "Under Review",
    "approvedBy": "Finance Director",
    "approvalDate": null,
    "priority": "Low",
    "impact": "Improved community welfare in commercial areas",
    "aiRecommendation": "Approve - Critical need",
    "confidenceScore": 93.4,
    "notes": "Standard procedure - Ikeja LGA",
    "createdDate": "2025-12-12T00:00:00"
  },
  {
    "id": 27,
    "decisionId": "DEC-2025-027",
    "decisionType": "Procurement",
    "subject": "Strategic equipment purchase - Ikeja Rhodes Park",
    "description": "Approve procurement for equipment in Ikeja",
    "amount": 8372747.0,
    "requestedBy": "Director of Administration",
    "requestDate": "2025-12-16T00:00:00",
    "status": "Under Review",
    "approvedBy": null,
    "approvalDate": "2026-01-17T00:00:00",
    "priority": "High",
    "impact": "Improved infrastructure in commercial areas",
    "aiRecommendation": "Defer pending review",
    "confidenceScore": 96.4,
    "notes": "Standard procedure - Ikeja LGA",
    "createdDate": "2025-12-03T00:00:00"
  },
  {
    "id": 28,
    "decisionId": "DEC-2025-028",
    "decisionType": "Infrastructure",
    "subject": "Planned project funding - Ikeja City Centre",
    "description": "Approve investment for facilities in Ikeja",
    "amount": 14807899.0,
    "requestedBy": "Director of Planning",
    "requestDate": "2025-12-27T00:00:00",
    "status": "Rejected",
    "approvedBy": null,
    "approvalDate": "2026-01-16T00:00:00",
    "priority": "Critical",
    "impact": "Improved infrastructure in commercial areas",
    "aiRecommendation": "Approve - Critical need",
    "confidenceScore": 81.9,
    "notes": "Urgent action required - Ikeja LGA",
    "createdDate": "2025-11-14T00:00:00"
  },
  {
    "id": 29,
    "decisionId": "DEC-2025-029",
    "decisionType": "Contract",
    "subject": "Planned project funding - Ikeja City Centre",
    "description": "Approve budget allocation for infrastructure in Ikeja",
    "amount": 9542895.0,
    "requestedBy": "Director of Health",
    "requestDate": "2025-12-08T00:00:00",
    "status": "Pending",
    "approvedBy": null,
    "approvalDate": null,
    "priority": "Low",
    "impact": "Improved efficiency in residential areas",
    "aiRecommendation": "Review budget",
    "confidenceScore": 90.7,
    "notes": "Standard procedure - Ikeja LGA",
    "createdDate": "2025-12-18T00:00:00"
  },
  {
    "id": 30,
    "decisionId": "DEC-2025-030",
    "decisionType": "Infrastructure",
    "subject": "Strategic service expansion - Ikeja Chilenje",
    "description": "Approve investment for infrastructure in Ikeja",
    "amount": 17357578.0,
    "requestedBy": "Director of Finance",
    "requestDate": "2025-12-10T00:00:00",
    "status": "Pending",
    "approvedBy": null,
    "approvalDate": null,
    "priority": "Low",
    "impact": "Improved efficiency in low-density areas",
    "aiRecommendation": "Approve with conditions",
    "confidenceScore": 86.9,
    "notes": "Urgent action required - Ikeja LGA",
    "createdDate": "2025-11-24T00:00:00"
  }
]